[
  {
    "category_name": "Paper Bags",
    "category_thumbnail": "http://3.imimg.com/data3/CF/WT/GLADMIN-650/paper-bags-125x125.jpg",
    "items": [
      {
        "name": "Paper Carry Bags",
        "page": "https://dir.indiamart.com/impcat/paper-carry-bags.html",
        "thumbnail": "http://5.imimg.com/data5/GLADMIN/Default/2022/6/EZ/ZB/CE/92368/paper-carry-bags-125x125.jpg"
      },
      {
        "name": "Kraft Paper Bags",
        "page": "https://dir.indiamart.com/impcat/kraft-paper-bags.html",
        "thumbnail": "http://3.imimg.com/data3/DJ/AF/GLADMIN-10550/kraft-paper-bags-125x125.jpg"
      },
      {
        "name": "Printed Paper Bag",
        "page": "https://dir.indiamart.com/impcat/printed-paper-bag.html",
        "thumbnail": "http://5.imimg.com/data5/GLADMIN/Default/2022/1/VY/HK/YV/86648/printed-paper-bag-125x125.jpg"
      },
      {
        "name": "Paper Courier Bag",
        "page": "https://dir.indiamart.com/impcat/paper-courier-bag.html",
        "thumbnail": "http://5.imimg.com/data5/GLADMIN/Default/2021/2/BH/WZ/MU/81953/paper-courier-bag-125x125.jpg"
      },
      {
        "name": "Paper Shopping Bags",
        "page": "https://dir.indiamart.com/impcat/paper-shopping-bags.html",
        "thumbnail": "http://3.imimg.com/data3/XU/IK/MY-2/paper-shopping-bags-125x125.jpg"
      },
      {
        "name": "Brown Paper Bag",
        "page": "https://dir.indiamart.com/impcat/brown-paper-bag.html",
        "thumbnail": "http://3.imimg.com/data3/DU/XQ/GLADMIN-95974/brown-paper-bag-125x125.jpg"
      },
      {
        "name": "Paper Food Bag",
        "page": "https://dir.indiamart.com/impcat/paper-food-bag.html",
        "thumbnail": "http://3.imimg.com/data3/BX/RB/GLADMIN-99846/paper-food-bag-125x125.jpg"
      },
      {
        "name": "Paper Grocery Bag",
        "page": "https://dir.indiamart.com/impcat/paper-grocery-bag.html",
        "thumbnail": "http://3.imimg.com/data3/GK/EW/GLADMIN-95979/paper-grocery-bag-125x125.jpg"
      },
      {
        "name": "Paper Packaging Bag",
        "page": "https://dir.indiamart.com/impcat/paper-packaging-bag.html",
        "thumbnail": "http://3.imimg.com/data3/IT/HE/GLADMIN-95981/paper-packaging-bag-125x125.jpg"
      },
      {
        "name": "Customised Paper Bag",
        "page": "https://dir.indiamart.com/impcat/customised-paper-bag.html",
        "thumbnail": "http://3.imimg.com/data3/TB/KS/GLADMIN-121122/customised-paper-bag-125x125.jpg"
      },
      {
        "name": "Medical Packaging Cover",
        "page": "https://dir.indiamart.com/impcat/medical-packaging-cover.html",
        "thumbnail": "http://3.imimg.com/data3/PS/SN/GLADMIN-46001/medical-packaging-cover-125x125.jpg"
      },
      {
        "name": "Sweet Bags",
        "page": "https://dir.indiamart.com/impcat/sweet-bags.html",
        "thumbnail": "http://5.imimg.com/data5/GLADMIN/Default/2021/9/KY/QF/IV/86664/sweet-bags-125x125.jpg"
      },
      {
        "name": "Butter Paper Bags",
        "page": "https://dir.indiamart.com/impcat/butter-paper-bags.html",
        "thumbnail": "http://5.imimg.com/data5/GLADMIN/Default/2021/9/MN/ZL/YM/84715/butter-paper-bags-125x125.jpg"
      },
      {
        "name": "Designer Paper Bag",
        "page": "https://dir.indiamart.com/impcat/designer-paper-bag.html",
        "thumbnail": "http://3.imimg.com/data3/TQ/RN/GLADMIN-121127/designer-paper-bag-125x125.jpg"
      },
      {
        "name": "Loop Handle Paper Bag",
        "page": "https://dir.indiamart.com/impcat/loop-handle-paper-bag.html",
        "thumbnail": "http://5.imimg.com/data5/EW/IF/CD/GLADMIN-68087/loop-handle-paper-bag-125x125.jpg"
      },
      {
        "name": "Paper Products",
        "page": "https://dir.indiamart.com/impcat/paper-products.html",
        "thumbnail": "http://3.imimg.com/data3/TV/BB/GLADMIN-113936/paper-products-125x125.jpg"
      },
      {
        "name": "Newspaper Bags",
        "page": "https://dir.indiamart.com/impcat/newspaper-bags.html",
        "thumbnail": "http://3.imimg.com/data3/AN/AT/GLADMIN-32670/newspaper-bags-125x125.jpg"
      },
      {
        "name": "Handmade Paper Bags",
        "page": "https://dir.indiamart.com/impcat/handmade-paper-bags.html",
        "thumbnail": "http://3.imimg.com/data3/XK/FJ/GLADMIN-11850/handmade-paper-bags-125x125.jpg"
      },
      {
        "name": "Laminated Paper Bag",
        "page": "https://dir.indiamart.com/impcat/laminated-paper-bag.html",
        "thumbnail": "http://5.imimg.com/data5/GLADMIN/Default/2024/1/375210694/OB/RI/RC/90525/laminated-paper-bag-125x125.png"
      },
      {
        "name": "Eco Friendly Paper Bags",
        "page": "https://dir.indiamart.com/impcat/eco-friendly-paper-bags.html",
        "thumbnail": "http://3.imimg.com/data3/CY/NW/GLADMIN-152936/eco-friendly-paper-bags-125x125.jpg"
      },
      {
        "name": "SOS Paper Bag",
        "page": "https://dir.indiamart.com/impcat/sos-paper-bag.html",
        "thumbnail": "http://3.imimg.com/data3/BB/QL/GLADMIN-117543/sos-paper-bag-125x125.jpg"
      },
      {
        "name": "Paper Craft Bag",
        "page": "https://dir.indiamart.com/impcat/paper-craft-bag.html",
        "thumbnail": "http://3.imimg.com/data3/WE/NF/GLADMIN-99373/paper-craft-bag-125x125.jpg"
      },
      {
        "name": "Multiwall Paper Bags",
        "page": "https://dir.indiamart.com/impcat/multiwall-paper-bags.html",
        "thumbnail": "http://3.imimg.com/data3/HA/PO/GLADMIN-85662/multiwall-paper-bags-125x125.jpg"
      },
      {
        "name": "Wine Paper Bag",
        "page": "https://dir.indiamart.com/impcat/wine-paper-bag.html",
        "thumbnail": "http://3.imimg.com/data3/VY/YP/GLADMIN-118007/wine-paper-bag-125x125.jpg"
      },
      {
        "name": "D Cut Paper Bags",
        "page": "https://dir.indiamart.com/impcat/d-cut-paper-bags.html",
        "thumbnail": "http://5.imimg.com/data5/HO/UY/VT/GLADMIN-68087/d-cut-paper-bags-125x125.jpg"
      },
      {
        "name": "Waterproof Paper Bag",
        "page": "https://dir.indiamart.com/impcat/waterproof-paper-bag.html",
        "thumbnail": "http://5.imimg.com/data5/LV/VY/FW/GLADMIN-73621/waterproof-paper-bag-125x125.png"
      },
      {
        "name": "Promotional Paper Bag",
        "page": "https://dir.indiamart.com/impcat/promotional-paper-bag.html",
        "thumbnail": "http://3.imimg.com/data3/RH/QW/GLADMIN-132991/promotional-paper-bag-125x125.jpg"
      },
      {
        "name": "Paper Sack",
        "page": "https://dir.indiamart.com/impcat/paper-sack.html",
        "thumbnail": "http://3.imimg.com/data3/VS/JQ/GLADMIN-95982/paper-sack-125x125.jpg"
      },
      {
        "name": "Paper Handbag",
        "page": "https://dir.indiamart.com/impcat/paper-handbag.html",
        "thumbnail": "http://3.imimg.com/data3/YF/RP/GLADMIN-74506/paper-handbag-125x125.jpg"
      },
      {
        "name": "Paper Dust Bag",
        "page": "https://dir.indiamart.com/impcat/paper-dust-bag.html",
        "thumbnail": "http://3.imimg.com/data3/FK/BT/GLADMIN-85237/paper-dust-bag-125x125.jpg"
      },
      {
        "name": "Duplex Paper Bag",
        "page": "https://dir.indiamart.com/impcat/duplex-paper-bag.html",
        "thumbnail": "http://3.imimg.com/data3/HM/XB/GLADMIN-121136/duplex-paper-bag-125x125.jpg"
      },
      {
        "name": "Chemical Paper Bag",
        "page": "https://dir.indiamart.com/impcat/chemical-paper-bag.html",
        "thumbnail": "http://3.imimg.com/data3/DO/UQ/GLADMIN-95975/chemical-paper-bag-125x125.jpg"
      },
      {
        "name": "Flat Paper Bag",
        "page": "https://dir.indiamart.com/impcat/flat-paper-bag.html",
        "thumbnail": "http://3.imimg.com/data3/CV/CC/GLADMIN-88154/flat-paper-bag-125x125.jpg"
      },
      {
        "name": "Advertising Paper Bag",
        "page": "https://dir.indiamart.com/impcat/advertising-paper-bag.html",
        "thumbnail": "http://3.imimg.com/data3/JW/FB/GLADMIN-45578/advertising-paper-bag-125x125.jpg"
      },
      {
        "name": "Paper Coffee Bag",
        "page": "https://dir.indiamart.com/impcat/paper-coffee-bag.html",
        "thumbnail": "http://3.imimg.com/data3/QT/MC/GLADMIN-74504/paper-coffee-bag-125x125.jpg"
      },
      {
        "name": "Recycled Paper Bag",
        "page": "https://dir.indiamart.com/impcat/recycled-paper-bag.html",
        "thumbnail": "http://4.imimg.com/data4/FL/IO/GLADMIN-2/recycled-paper-bag-125x125.jpg"
      },
      {
        "name": "Art Paper Bag",
        "page": "https://dir.indiamart.com/impcat/art-paper-bag.html",
        "thumbnail": "http://3.imimg.com/data3/OD/DU/GLADMIN-121072/art-paper-bag-125x125.jpg"
      },
      {
        "name": "Carton Bags",
        "page": "https://dir.indiamart.com/impcat/carton-bags.html",
        "thumbnail": "http://5.imimg.com/data5/EE/EE/GLADMIN-/carton-bags-125x125.jpg"
      },
      {
        "name": "Textured Paper Bags",
        "page": "https://dir.indiamart.com/impcat/textured-paper-bags.html",
        "thumbnail": "http://3.imimg.com/data3/TW/EI/GLADMIN-146460/textured-paper-bags-125x125.jpg"
      },
      {
        "name": "Paper Carrier Bag",
        "page": "https://dir.indiamart.com/impcat/paper-carrier-bag.html",
        "thumbnail": "http://3.imimg.com/data3/NI/IG/GLADMIN-85670/paper-carrier-bag-125x125.jpg"
      },
      {
        "name": "Handmade Paper Wine Bags",
        "page": "https://dir.indiamart.com/impcat/handmade-paper-wine-bags.html",
        "thumbnail": "http://3.imimg.com/data3/EL/LI/GLADMIN-11860/handmade-paper-wine-bags-125x125.jpg"
      }
    ]
  },
  {
    "category_name": "Posters",
    "category_thumbnail": "http://3.imimg.com/data3/CC/RY/GLADMIN-20735/posters-125x125.jpg",
    "items": [
      {
        "name": "Printed Poster",
        "page": "https://dir.indiamart.com/impcat/printed-poster.html",
        "thumbnail": "http://5.imimg.com/data5/GLADMIN/Default/2022/1/IW/MQ/EX/56704/printed-poster-125x125.jpg"
      },
      {
        "name": "Poster Printing",
        "page": "https://dir.indiamart.com/impcat/poster-printing.html",
        "thumbnail": "http://3.imimg.com/data3/FL/ED/GLADMIN-42032/poster-printing-125x125.jpg"
      },
      {
        "name": "Wall Posters",
        "page": "https://dir.indiamart.com/impcat/wall-posters.html",
        "thumbnail": "http://3.imimg.com/data3/IJ/XQ/GLADMIN-20734/wall-posters-125x125.jpg"
      },
      {
        "name": "Safety Poster",
        "page": "https://dir.indiamart.com/impcat/safety-poster.html",
        "thumbnail": "http://5.imimg.com/data5/GLADMIN/Default/2022/7/XU/EX/LZ/92368/safety-poster-125x125.jpg"
      },
      {
        "name": "Poster Paper",
        "page": "https://dir.indiamart.com/impcat/poster-paper.html",
        "thumbnail": "http://3.imimg.com/data3/PA/AW/GLADMIN-107155/poster-paper-125x125.jpg"
      },
      {
        "name": "3D Posters",
        "page": "https://dir.indiamart.com/impcat/3d-posters.html",
        "thumbnail": "http://3.imimg.com/data3/EP/DG/GLADMIN-148755/3d-posters-125x125.jpg"
      },
      {
        "name": "Digital Poster Printing Services",
        "page": "https://dir.indiamart.com/impcat/digital-poster-printing-services.html",
        "thumbnail": "http://3.imimg.com/data3/UA/HE/GLADMIN-170381/digital-poster-printing-services-125x125.jpg"
      },
      {
        "name": "Poster Designing",
        "page": "https://dir.indiamart.com/impcat/poster-designing.html",
        "thumbnail": "http://3.imimg.com/data3/GF/RX/GLADMIN-147945/poster-designing-125x125.jpg"
      },
      {
        "name": "Religious Posters",
        "page": "https://dir.indiamart.com/impcat/religious-posters.html",
        "thumbnail": "http://5.imimg.com/data5/GLADMIN/Default/2021/11/DF/EJ/XZ/81953/religious-posters-125x125.png"
      },
      {
        "name": "Motivational Posters",
        "page": "https://dir.indiamart.com/impcat/motivational-posters.html",
        "thumbnail": "http://4.imimg.com/data4/BN/TY/GLADMIN-2/motivational-posters-125x125.jpg"
      },
      {
        "name": "Promotional Posters",
        "page": "https://dir.indiamart.com/impcat/promotional-posters.html",
        "thumbnail": "http://4.imimg.com/data4/OF/HY/GLADMIN-2/promotional-posters-125x125.jpg"
      },
      {
        "name": "Birthday Poster",
        "page": "https://dir.indiamart.com/impcat/birthday-poster.html",
        "thumbnail": "http://5.imimg.com/data5/WI/EC/YJ/GLADMIN-68155/birthday-poster-125x125.jpg"
      },
      {
        "name": "Thermoformed Posters",
        "page": "https://dir.indiamart.com/impcat/thermoformed-posters.html",
        "thumbnail": "http://3.imimg.com/data3/XD/QK/GLADMIN-107156/thermoformed-posters-125x125.jpg"
      },
      {
        "name": "Electrical Safety Poster",
        "page": "https://dir.indiamart.com/impcat/electrical-safety-poster.html",
        "thumbnail": "http://4.imimg.com/data4/RN/FF/GLADMIN-2/electrical-safety-poster-125x125.jpg"
      },
      {
        "name": "Fire Safety Posters",
        "page": "https://dir.indiamart.com/impcat/fire-safety-posters.html",
        "thumbnail": "http://4.imimg.com/data4/AS/VY/GLADMIN-2/fire-safety-posters-125x125.jpg"
      },
      {
        "name": "Construction Safety Posters",
        "page": "https://dir.indiamart.com/impcat/construction-safety-posters.html",
        "thumbnail": "http://5.imimg.com/data5/FF/FF/GLADMIN-/construction-safety-posters-125x125.gif"
      }
    ]
  },
  {
    "category_name": "Storage Boxes",
    "category_thumbnail": "http://3.imimg.com/data3/HQ/FY/GLADMIN-38213/storage-boxes-125x125.jpg",
    "items": [
      {
        "name": "Storage Organizer",
        "page": "https://dir.indiamart.com/impcat/storage-organizer.html",
        "thumbnail": "http://3.imimg.com/data3/VV/FC/GLADMIN-43216/storage-organizer-125x125.jpg"
      },
      {
        "name": "Closet Organizers",
        "page": "https://dir.indiamart.com/impcat/closet-organizers.html",
        "thumbnail": "http://3.imimg.com/data3/NC/MR/GLADMIN-25022/closet-organizers-125x125.jpg"
      },
      {
        "name": "Shelf Organizer",
        "page": "https://dir.indiamart.com/impcat/shelf-organizer.html",
        "thumbnail": "http://3.imimg.com/data3/CE/MD/GLADMIN-95049/shelf-organizer-125x125.jpg"
      },
      {
        "name": "File Boxes",
        "page": "https://dir.indiamart.com/impcat/file-boxes.html",
        "thumbnail": "http://3.imimg.com/data3/UT/NS/GLADMIN-27462/file-boxes-125x125.jpg"
      },
      {
        "name": "Storage Cube",
        "page": "https://dir.indiamart.com/impcat/storage-cube.html",
        "thumbnail": "http://3.imimg.com/data3/XB/XQ/GLADMIN-89984/storage-cube-125x125.jpg"
      },
      {
        "name": "Office Storage Boxes",
        "page": "https://dir.indiamart.com/impcat/office-storage-boxes.html",
        "thumbnail": "http://3.imimg.com/data3/FI/WC/GLADMIN-112867/office-storage-boxes-125x125.jpg"
      },
      {
        "name": "Archive Boxes",
        "page": "https://dir.indiamart.com/impcat/archive-boxes.html",
        "thumbnail": "http://3.imimg.com/data3/DE/GP/GLADMIN-99611/archive-boxes-125x125.jpg"
      }
    ]
  },
  {
    "category_name": "Paper Tube",
    "category_thumbnail": "http://3.imimg.com/data3/OA/EK/GLADMIN-5745/paper-tube-125x125.jpg",
    "items": [
      {
        "name": "Paper Cores",
        "page": "https://dir.indiamart.com/impcat/paper-cores.html",
        "thumbnail": "http://3.imimg.com/data3/XA/HQ/GLADMIN-5716/paper-cores-125x125.jpg"
      },
      {
        "name": "Packaging Paper Tube",
        "page": "https://dir.indiamart.com/impcat/packaging-paper-tube.html",
        "thumbnail": "http://3.imimg.com/data3/NP/ED/GLADMIN-160590/packaging-paper-tube-125x125.jpg"
      },
      {
        "name": "Paper Core Tube",
        "page": "https://dir.indiamart.com/impcat/paper-core-tube.html",
        "thumbnail": "http://3.imimg.com/data3/BT/PL/GLADMIN-166450/paper-core-tube-125x125.jpg"
      },
      {
        "name": "Kraft Paper Tubes",
        "page": "https://dir.indiamart.com/impcat/kraft-paper-tubes.html",
        "thumbnail": "http://3.imimg.com/data3/QR/UW/GLADMIN-146577/kraft-paper-tubes-125x125.jpg"
      },
      {
        "name": "Cardboard Tube",
        "page": "https://dir.indiamart.com/impcat/cardboard-tube.html",
        "thumbnail": "http://3.imimg.com/data3/YH/HW/GLADMIN-136743/cardboard-tube-125x125.jpg"
      },
      {
        "name": "Spiral Paper Core",
        "page": "https://dir.indiamart.com/impcat/spiral-paper-core.html",
        "thumbnail": "http://5.imimg.com/data5/GLADMIN/Default/2024/1/375216074/PD/RM/BX/90525/spiral-paper-core-125x125.png"
      },
      {
        "name": "Textile Paper Tube",
        "page": "https://dir.indiamart.com/impcat/textile-paper-tube.html",
        "thumbnail": "http://3.imimg.com/data3/FH/IF/GLADMIN-160596/textile-paper-tube-125x125.jpg"
      },
      {
        "name": "Spiral Paper Tube",
        "page": "https://dir.indiamart.com/impcat/spiral-paper-tube.html",
        "thumbnail": "http://4.imimg.com/data4/QP/FR/GLADMIN-179311/spiral-paper-tube-125x125.jpg"
      },
      {
        "name": "Poster Tube",
        "page": "https://dir.indiamart.com/impcat/poster-tube.html",
        "thumbnail": "http://5.imimg.com/data5/HF/TD/GLADMIN-2/poster-tube-125x125.jpg"
      },
      {
        "name": "Recycled Paper Tube",
        "page": "https://dir.indiamart.com/impcat/recycled-paper-tube.html",
        "thumbnail": "http://4.imimg.com/data4/GI/VD/GLADMIN-185031/recycled-paper-tube-125x125.png"
      },
      {
        "name": "Crepe Paper Tube",
        "page": "https://dir.indiamart.com/impcat/crepe-paper-tube.html",
        "thumbnail": "http://3.imimg.com/data3/YW/YI/GLADMIN-151694/crepe-paper-tube-125x125.png"
      },
      {
        "name": "Embossed Paper Tube",
        "page": "https://dir.indiamart.com/impcat/embossed-paper-tube.html",
        "thumbnail": "http://3.imimg.com/data3/JY/VJ/GLADMIN-160581/embossed-paper-tube-125x125.jpg"
      }
    ]
  },
  {
    "category_name": "Paperboard",
    "category_thumbnail": "http://3.imimg.com/data3/BV/XE/GLADMIN-34529/paperboard-125x125.jpg",
    "items": [
      {
        "name": "Cardboard Sheets",
        "page": "https://dir.indiamart.com/impcat/cardboard-sheets.html",
        "thumbnail": "http://3.imimg.com/data3/AI/KN/GLADMIN-145016/cardboard-sheets-125x125.jpg"
      },
      {
        "name": "Grey Board",
        "page": "https://dir.indiamart.com/impcat/grey-board.html",
        "thumbnail": "http://3.imimg.com/data3/SQ/NE/GLADMIN-21025/grey-board-125x125.jpg"
      },
      {
        "name": "Kappa Paper Board",
        "page": "https://dir.indiamart.com/impcat/kappa-paper.html",
        "thumbnail": "http://5.imimg.com/data5/DB/IF/EK/GLADMIN-68087/kappa-paper-125x125.jpg"
      },
      {
        "name": "Millboard",
        "page": "https://dir.indiamart.com/impcat/millboard.html",
        "thumbnail": "http://3.imimg.com/data3/WH/BO/GLADMIN-33237/millboard-125x125.jpg"
      },
      {
        "name": "Hard Board Paper",
        "page": "https://dir.indiamart.com/impcat/hard-board-paper.html",
        "thumbnail": "http://3.imimg.com/data3/EW/AP/GLADMIN-121055/hard-board-paper-125x125.jpg"
      },
      {
        "name": "Mill Board Paper",
        "page": "https://dir.indiamart.com/impcat/mill-board-paper.html",
        "thumbnail": "http://5.imimg.com/data5/GLADMIN/Default/2023/12/369973515/GI/XU/NH/80176/mill-board-paper-125x125.jpg"
      },
      {
        "name": "Kraft Paperboard",
        "page": "https://dir.indiamart.com/impcat/kraft-paperboard.html",
        "thumbnail": "http://3.imimg.com/data3/WN/XY/GLADMIN-31377/kraft-paperboard-125x125.jpg"
      },
      {
        "name": "Solid Bleached Sulfate Board",
        "page": "https://dir.indiamart.com/impcat/solid-bleached-sulfate-board.html",
        "thumbnail": "http://4.imimg.com/data4/RP/XU/GLADMIN-166771/solid-bleached-sulfate-board-125x125.jpg"
      },
      {
        "name": "Pressboard",
        "page": "https://dir.indiamart.com/impcat/pressboard.html",
        "thumbnail": "http://3.imimg.com/data3/IE/FT/GLADMIN-35621/pressboard-125x125.jpg"
      },
      {
        "name": "Book Binding Boards",
        "page": "https://dir.indiamart.com/impcat/book-binding-boards.html",
        "thumbnail": "http://3.imimg.com/data3/EG/GY/GLADMIN-164529/book-binding-boards-125x125.jpg"
      },
      {
        "name": "Folding Box Board",
        "page": "https://dir.indiamart.com/impcat/folding-box-board.html",
        "thumbnail": "http://3.imimg.com/data3/NK/WJ/MY-2/image-php-125x125.jpg"
      },
      {
        "name": "Coated Paper Board",
        "page": "https://dir.indiamart.com/impcat/coated-paper-board.html",
        "thumbnail": "http://4.imimg.com/data4/TD/VW/GLADMIN-185453/coated-paper-board-125x125.jpg"
      },
      {
        "name": "Pulp Board",
        "page": "https://dir.indiamart.com/impcat/pulp-board.html",
        "thumbnail": "http://3.imimg.com/data3/VM/EP/GLADMIN-74511/pulp-board-125x125.jpg"
      },
      {
        "name": "Bristol Board",
        "page": "https://dir.indiamart.com/impcat/bristol-board.html",
        "thumbnail": "http://3.imimg.com/data3/RY/RL/GLADMIN-23609/bristol-board-125x125.jpg"
      },
      {
        "name": "Manila Board",
        "page": "https://dir.indiamart.com/impcat/manila-board.html",
        "thumbnail": "http://4.imimg.com/data4/SJ/GE/GLADMIN-185105/manila-board-125x125.jpg"
      }
    ]
  },
  {
    "category_name": "Paper Cans",
    "category_thumbnail": "http://4.imimg.com/data4/DV/UG/GLADMIN-178672/paper-cans-125x125.jpg",
    "items": [
      {
        "name": "Paper Containers",
        "page": "https://dir.indiamart.com/impcat/paper-containers.html",
        "thumbnail": "http://3.imimg.com/data3/GA/AW/GLADMIN-5714/paper-containers-125x125.jpg"
      },
      {
        "name": "Fibre Drums",
        "page": "https://dir.indiamart.com/impcat/fibre-drums.html",
        "thumbnail": "http://3.imimg.com/data3/NG/VO/GLADMIN-6323/fibre-drums-125x125.jpg"
      },
      {
        "name": "Composite Can",
        "page": "https://dir.indiamart.com/impcat/composite-can.html",
        "thumbnail": "http://3.imimg.com/data3/IL/ON/GLADMIN-56044/composite-can-125x125.jpg"
      },
      {
        "name": "Round Paper Container",
        "page": "https://dir.indiamart.com/impcat/round-paper-container.html",
        "thumbnail": "http://5.imimg.com/data5/TT/TT/GLADMIN-/round-paper-container-125x125.jpg"
      },
      {
        "name": "Composite Paper Container",
        "page": "https://dir.indiamart.com/impcat/composite-paper-container.html",
        "thumbnail": "http://5.imimg.com/data5/GLADMIN/Default/2024/6/429790265/OY/LQ/ZD/90525/composite-paper-container-125x125.png"
      },
      {
        "name": "Mailing Tubes",
        "page": "https://dir.indiamart.com/impcat/mailing-tubes.html",
        "thumbnail": "http://3.imimg.com/data3/ON/QB/GLADMIN-31762/mailing-tubes-125x125.jpg"
      },
      {
        "name": "Paper Drum",
        "page": "https://dir.indiamart.com/impcat/paper-drum.html",
        "thumbnail": "http://3.imimg.com/data3/PT/CI/GLADMIN-42910/paper-drum-125x125.jpg"
      },
      {
        "name": "Composite Containers",
        "page": "https://dir.indiamart.com/impcat/composite-containers.html",
        "thumbnail": "http://3.imimg.com/data3/LD/HF/GLADMIN-3951/composite-containers-125x125.jpg"
      },
      {
        "name": "Packaging Drum",
        "page": "https://dir.indiamart.com/impcat/packaging-drum.html",
        "thumbnail": "http://3.imimg.com/data3/TX/MG/GLADMIN-95342/packaging-drum-125x125.jpg"
      },
      {
        "name": "Fibre Containers",
        "page": "https://dir.indiamart.com/impcat/fibre-containers.html",
        "thumbnail": "http://3.imimg.com/data3/VI/BB/GLADMIN-27436/fibre-containers-125x125.jpg"
      },
      {
        "name": "Paperboard Drums",
        "page": "https://dir.indiamart.com/impcat/paperboard-drums.html",
        "thumbnail": "http://3.imimg.com/data3/QR/SM/GLADMIN-42909/paperboard-drums-125x125.jpg"
      }
    ]
  },
  {
    "category_name": "Paper Card",
    "category_thumbnail": "http://3.imimg.com/data3/YM/FC/GLADMIN-33856/paper-card-125x125.jpg",
    "items": [
      {
        "name": "Sticker Paper",
        "page": "https://dir.indiamart.com/impcat/sticker-paper.html",
        "thumbnail": "http://3.imimg.com/data3/SH/WU/GLADMIN-38837/sticker-paper-125x125.jpg"
      },
      {
        "name": "Coin Packing Cards",
        "page": "https://dir.indiamart.com/impcat/coin-cards.html",
        "thumbnail": "http://5.imimg.com/data5/GLADMIN/Default/2021/8/LP/DE/YD/85357/coin-packing-cards-125x125.PNG"
      },
      {
        "name": "Packing Card",
        "page": "https://dir.indiamart.com/impcat/packing-card.html",
        "thumbnail": "http://5.imimg.com/data5/GLADMIN/Default/2021/7/VW/GP/NP/84715/packing-card-125x125.jpg"
      },
      {
        "name": "Gloss Art Card",
        "page": "https://dir.indiamart.com/impcat/gloss-art-card.html",
        "thumbnail": "http://3.imimg.com/data3/VD/XO/GLADMIN-142683/gloss-art-card-125x125.jpg"
      },
      {
        "name": "Table Tent Cards",
        "page": "https://dir.indiamart.com/impcat/table-tent-cards.html",
        "thumbnail": "http://3.imimg.com/data3/PA/HB/GLADMIN-74377/table-tent-cards-125x125.jpg"
      },
      {
        "name": "Paper Header Card",
        "page": "https://dir.indiamart.com/impcat/paper-header-card.html",
        "thumbnail": "http://3.imimg.com/data3/JI/MI/GLADMIN-88155/paper-header-card-125x125.jpg"
      },
      {
        "name": "Ivory Cards",
        "page": "https://dir.indiamart.com/impcat/ivory-cards.html",
        "thumbnail": "http://5.imimg.com/data5/QQ/QQ/GLADMIN-/ivory-cards-125x125.jpg"
      },
      {
        "name": "Paper Gift Card",
        "page": "https://dir.indiamart.com/impcat/paper-gift-card.html",
        "thumbnail": "http://3.imimg.com/data3/OB/NP/GLADMIN-99374/paper-gift-card-125x125.jpg"
      }
    ]
  },
  {
    "category_name": "Paper, Plastic, PET, Shrink Sleeves",
    "category_thumbnail": "http://5.imimg.com/data5/GLADMIN/Default/2021/7/XK/AG/OW/84715/paper-sleeves-125x125.jpg",
    "items": [
      {
        "name": "Shrink Sleeves",
        "page": "https://dir.indiamart.com/impcat/shrink-sleeves.html",
        "thumbnail": "http://3.imimg.com/data3/FL/GK/GLADMIN-1851/shrink-sleeves-125x125.jpg"
      },
      {
        "name": "Ice Cream Cone Sleeve",
        "page": "https://dir.indiamart.com/impcat/ice-cream-cone-sleeve.html",
        "thumbnail": "http://3.imimg.com/data3/WI/GP/GLADMIN-155900/ice-cream-cone-sleeve-125x125.jpg"
      },
      {
        "name": "Bottle Sleeve",
        "page": "https://dir.indiamart.com/impcat/bottle-sleeve.html",
        "thumbnail": "http://3.imimg.com/data3/NV/PV/GLADMIN-88125/bottle-sleeve-125x125.jpg"
      },
      {
        "name": "Packaging Sleeves",
        "page": "https://dir.indiamart.com/impcat/packaging-sleeves.html",
        "thumbnail": "http://3.imimg.com/data3/YX/BX/GLADMIN-88129/packaging-sleeves-125x125.jpg"
      },
      {
        "name": "Paper Cup Sleeve",
        "page": "https://dir.indiamart.com/impcat/paper-cup-sleeve.html",
        "thumbnail": "http://3.imimg.com/data3/UI/BQ/GLADMIN-111747/paper-cup-sleeve-125x125.jpg"
      },
      {
        "name": "Cup Sleeve",
        "page": "https://dir.indiamart.com/impcat/cup-sleeve.html",
        "thumbnail": "http://3.imimg.com/data3/BH/GT/GLADMIN-83958/cup-sleeve-125x125.jpg"
      }
    ]
  },
  {
    "category_name": "Paper Cones",
    "category_thumbnail": "http://3.imimg.com/data3/EN/WS/GLADMIN-1442/paper-cones-125x125.jpg",
    "items": [
      {
        "name": "Textile Paper Cone",
        "page": "https://dir.indiamart.com/impcat/textile-paper-cone.html",
        "thumbnail": "http://3.imimg.com/data3/DO/PP/GLADMIN-145374/textile-paper-cone-125x125.jpg"
      },
      {
        "name": "Yarn Cones",
        "page": "https://dir.indiamart.com/impcat/yarn-cones.html",
        "thumbnail": "http://3.imimg.com/data3/TL/TJ/GLADMIN-41675/yarn-cones-125x125.jpg"
      },
      {
        "name": "Printed Paper Cones",
        "page": "https://dir.indiamart.com/impcat/printed-paper-cones.html",
        "thumbnail": "http://3.imimg.com/data3/MV/JD/GLADMIN-8677/printed-paper-cones-125x125.jpg"
      },
      {
        "name": "Kraft Paper Cone",
        "page": "https://dir.indiamart.com/impcat/kraft-paper-cone.html",
        "thumbnail": "http://3.imimg.com/data3/PH/PX/GLADMIN-145372/kraft-paper-cone-125x125.jpg"
      },
      {
        "name": "Tight Bond Paper Cone",
        "page": "https://dir.indiamart.com/impcat/tight-bond-paper-cone.html",
        "thumbnail": "http://3.imimg.com/data3/GV/CJ/GLADMIN-145375/tight-bond-paper-cone-125x125.jpg"
      },
      {
        "name": "Waxed Paper Cone",
        "page": "https://dir.indiamart.com/impcat/waxed-paper-cone.html",
        "thumbnail": "http://3.imimg.com/data3/KA/UI/GLADMIN-107157/waxed-paper-cone-125x125.jpg"
      },
      {
        "name": "Cardboard Cone",
        "page": "https://dir.indiamart.com/impcat/cardboard-cone.html",
        "thumbnail": "http://3.imimg.com/data3/CN/WC/GLADMIN-145369/cardboard-cone-125x125.jpg"
      }
    ]
  },
  {
    "category_name": "Paper Crafts",
    "category_thumbnail": "http://3.imimg.com/data3/QD/FY/GLADMIN-33954/paper-crafts-125x125.jpg",
    "items": [
      {
        "name": "Paper Mache Handicraft",
        "page": "https://dir.indiamart.com/impcat/paper-mache.html",
        "thumbnail": "http://3.imimg.com/data3/DO/QO/GLADMIN-136047/paper-mache-handicraft-125x125.jpg"
      },
      {
        "name": "Paper Mache Boxes",
        "page": "https://dir.indiamart.com/impcat/paper-mache-boxes.html",
        "thumbnail": "http://3.imimg.com/data3/DE/AK/GLADMIN-147270/paper-mache-boxes-125x125.jpg"
      },
      {
        "name": "Handmade Paper Crafts",
        "page": "https://dir.indiamart.com/impcat/handmade-paper-crafts.html",
        "thumbnail": "http://3.imimg.com/data3/LR/EO/GLADMIN-11851/handmade-paper-crafts-125x125.jpg"
      },
      {
        "name": "Paper Star",
        "page": "https://dir.indiamart.com/impcat/paper-star.html",
        "thumbnail": "http://3.imimg.com/data3/DL/TS/GLADMIN-147652/paper-star-125x125.jpg"
      },
      {
        "name": "Paper Sculpture",
        "page": "https://dir.indiamart.com/impcat/paper-sculpture.html",
        "thumbnail": "http://3.imimg.com/data3/EJ/OQ/MY-2/paper-sculpture-125x125.jpg"
      },
      {
        "name": "Moonrock Paper",
        "page": "https://dir.indiamart.com/impcat/moonrock-paper.html",
        "thumbnail": "http://3.imimg.com/data3/GG/IP/GLADMIN-17674/moonrock-paper-125x125.jpg"
      }
    ]
  },
  {
    "category_name": "Paper Box",
    "category_thumbnail": "http://5.imimg.com/data5/LV/FI/CB/GLADMIN-73289/paper-box-125x125.jpg",
    "items": [
      {
        "name": "Cake Box",
        "page": "https://dir.indiamart.com/impcat/cake-box.html",
        "thumbnail": "http://3.imimg.com/data3/YK/CF/GLADMIN-23061/cake-box-125x125.jpg"
      },
      {
        "name": "Soap Packing Box",
        "page": "https://dir.indiamart.com/impcat/soap-packing-box.html",
        "thumbnail": "http://5.imimg.com/data5/GLADMIN/Default/2022/6/TW/XE/EP/92368/soap-packing-box-125x125.jpg"
      },
      {
        "name": "Cosmetic Packaging Box",
        "page": "https://dir.indiamart.com/impcat/cosmetic-packaging-box.html",
        "thumbnail": "http://5.imimg.com/data5/GLADMIN/Default/2021/12/CA/IB/FT/85916/cosmetic-packaging-box-125x125.jpg"
      },
      {
        "name": "Agarbatti Paper Box",
        "page": "https://dir.indiamart.com/impcat/incense-stick-box.html",
        "thumbnail": "http://5.imimg.com/data5/XL/JO/OG/GLADMIN-68087/incense-stick-box-125x125.jpg"
      },
      {
        "name": "Paper Food Boxes",
        "page": "https://dir.indiamart.com/impcat/paper-food-boxes.html",
        "thumbnail": "http://5.imimg.com/data5/GLADMIN/Default/2021/12/JA/EM/NG/85916/paper-food-boxes-125x125.jpg"
      },
      {
        "name": "Mono Cartons",
        "page": "https://dir.indiamart.com/impcat/mono-cartons.html",
        "thumbnail": "http://5.imimg.com/data5/NR/PP/GF/GLADMIN-73289/mono-cartons-125x125.jpg"
      },
      {
        "name": "Electronics Packaging Box",
        "page": "https://dir.indiamart.com/impcat/electronics-packaging-boxes.html",
        "thumbnail": "http://5.imimg.com/data5/AC/OH/CU/GLADMIN-73289/electronics-packaging-box-125x125"
      },
      {
        "name": "Popcorn and French Fries Boxes",
        "page": "https://dir.indiamart.com/impcat/popcorn-boxes.html",
        "thumbnail": "http://5.imimg.com/data5/GLADMIN/Default/2021/12/JQ/EE/GO/85916/popcorn-boxes-125x125.jpg"
      },
      {
        "name": "Candle Boxes",
        "page": "https://dir.indiamart.com/impcat/candle-boxes.html",
        "thumbnail": "http://3.imimg.com/data3/BI/NK/GLADMIN-98581/candle-boxes-125x125.jpg"
      },
      {
        "name": "Spice Packaging Box",
        "page": "https://dir.indiamart.com/impcat/spice-packaging-box.html",
        "thumbnail": "http://5.imimg.com/data5/GLADMIN/Default/2021/9/LO/QU/YL/86664/spice-packaging-box-125x125.jpg"
      },
      {
        "name": "Burger Box",
        "page": "https://dir.indiamart.com/impcat/burger-box.html",
        "thumbnail": "http://4.imimg.com/data4/KB/UY/GLADMIN-181329/burger-box-125x125.jpg"
      },
      {
        "name": "Mobile Phone Boxes",
        "page": "https://dir.indiamart.com/impcat/cell-phone-boxes.html",
        "thumbnail": "http://5.imimg.com/data5/IT/DU/LL/GLADMIN-73289/cell-phone-boxes-125x125.jpg"
      },
      {
        "name": "Medicine Packaging Boxes",
        "page": "https://dir.indiamart.com/impcat/medicine-packaging-boxes.html",
        "thumbnail": "http://5.imimg.com/data5/OA/RA/YN/GLADMIN-73289/medicine-packaging-boxes-125x125.jpg"
      },
      {
        "name": "Duplex Boxes",
        "page": "https://dir.indiamart.com/impcat/duplex-boxes.html",
        "thumbnail": "http://5.imimg.com/data5/GLADMIN/Default/2021/8/MG/DA/IL/85916/duplex-boxes-125x125.jpg"
      },
      {
        "name": "Sandwich Boxes",
        "page": "https://dir.indiamart.com/impcat/sandwich-container.html",
        "thumbnail": "http://5.imimg.com/data5/PM/HS/GLADMIN-2/sandwich-container-125x125.jpg"
      },
      {
        "name": "Ice Cream Packaging Box",
        "page": "https://dir.indiamart.com/impcat/ice-cream-packaging-box.html",
        "thumbnail": "http://5.imimg.com/data5/GLADMIN/Default/2021/9/RX/OZ/DO/86664/ice-cream-packaging-box-125x125.jpg"
      },
      {
        "name": "LED Bulb Box",
        "page": "https://dir.indiamart.com/impcat/led-bulb-box.html",
        "thumbnail": "http://4.imimg.com/data4/AX/WY/GLADMIN-179966/led-bulb-box-125x125.jpg"
      },
      {
        "name": "Craft Box",
        "page": "https://dir.indiamart.com/impcat/craft-box.html",
        "thumbnail": "http://3.imimg.com/data3/KJ/JY/GLADMIN-83898/craft-box-125x125.jpg"
      },
      {
        "name": "Rakhi Box",
        "page": "https://dir.indiamart.com/impcat/rakhi-box.html",
        "thumbnail": "http://4.imimg.com/data4/EQ/CC/GLADMIN-183931/rakhi-box-125x125.jpg"
      },
      {
        "name": "Tube Light Packaging Box",
        "page": "https://dir.indiamart.com/impcat/tube-light-packaging-box.html",
        "thumbnail": "http://5.imimg.com/data5/SR/EX/FV/GLADMIN-73289/tube-light-packaging-box-125x125.jpg"
      },
      {
        "name": "Face Mask Packaging Box",
        "page": "https://dir.indiamart.com/impcat/face-mask-packaging-box.html",
        "thumbnail": "http://5.imimg.com/data5/GLADMIN/Default/2023/8/332138306/DL/ZX/AT/88875/face-mask-packaging-box-125x125.jpg"
      }
    ]
  }
]